{
  "cb4e58acdeea1cfb42b89a42126fbcc4" : {
    "statistic" : {
      "failed" : 0,
      "broken" : 0,
      "skipped" : 0,
      "passed" : 1,
      "unknown" : 0,
      "total" : 1
    },
    "items" : [ {
      "uid" : "66a92992b59a0e35",
      "reportUrl" : "https://plresearch999.github.io/cicd-py-example/2//#testresult/66a92992b59a0e35",
      "status" : "passed",
      "time" : {
        "start" : 1620900050459,
        "stop" : 1620900050459,
        "duration" : 0
      }
    } ]
  },
  "8b7d100b89a9b0e22a8d6732c7ee0ba9" : {
    "statistic" : {
      "failed" : 0,
      "broken" : 0,
      "skipped" : 0,
      "passed" : 1,
      "unknown" : 0,
      "total" : 1
    },
    "items" : [ {
      "uid" : "6cd030ebb7decf5b",
      "reportUrl" : "https://plresearch999.github.io/cicd-py-example/2//#testresult/6cd030ebb7decf5b",
      "status" : "passed",
      "time" : {
        "start" : 1620900050456,
        "stop" : 1620900050456,
        "duration" : 0
      }
    } ]
  },
  "dcb8fa11fdff83e2daf0e792014a33fe" : {
    "statistic" : {
      "failed" : 0,
      "broken" : 0,
      "skipped" : 0,
      "passed" : 1,
      "unknown" : 0,
      "total" : 1
    },
    "items" : [ {
      "uid" : "7827716ee8bf6e59",
      "reportUrl" : "https://plresearch999.github.io/cicd-py-example/2//#testresult/7827716ee8bf6e59",
      "status" : "passed",
      "time" : {
        "start" : 1620900050458,
        "stop" : 1620900050458,
        "duration" : 0
      }
    } ]
  },
  "dce78d7dd5962c01ca0a9a6e9bc9920e" : {
    "statistic" : {
      "failed" : 0,
      "broken" : 0,
      "skipped" : 0,
      "passed" : 1,
      "unknown" : 0,
      "total" : 1
    },
    "items" : [ {
      "uid" : "1a8babd30acfcedd",
      "reportUrl" : "https://plresearch999.github.io/cicd-py-example/2//#testresult/1a8babd30acfcedd",
      "status" : "passed",
      "time" : {
        "start" : 1620900050445,
        "stop" : 1620900050445,
        "duration" : 0
      }
    } ]
  }
}